yardee/__init__.py
yardee/client.py
yardee-0.1.0.dist-info/METADATA
yardee-0.1.0.dist-info/WHEEL
yardee-0.1.0.dist-info/licenses/LICENSE
yardee-0.1.0.dist-info/RECORD
