Metadata-Version: 2.4
Name: yardee
Version: 0.1.0
Summary: Official Python SDK for Yardee Vector Database API
Project-URL: Homepage, https://yardee.ai
Project-URL: Documentation, https://yardee.ai/customragbot-api/documentation
Project-URL: Repository, https://github.com/yardee-ai/yardee-python-sdk
Author-email: Yardee AI <support@yardee.ai>
License-Expression: MIT
License-File: LICENSE
Keywords: ai,chatbot,database,embedding,rag,search,vector
Classifier: Development Status :: 4 - Beta
Classifier: Intended Audience :: Developers
Classifier: License :: OSI Approved :: MIT License
Classifier: Programming Language :: Python :: 3
Classifier: Programming Language :: Python :: 3.8
Classifier: Programming Language :: Python :: 3.9
Classifier: Programming Language :: Python :: 3.10
Classifier: Programming Language :: Python :: 3.11
Classifier: Programming Language :: Python :: 3.12
Classifier: Topic :: Scientific/Engineering :: Artificial Intelligence
Classifier: Topic :: Software Development :: Libraries :: Python Modules
Requires-Python: >=3.8
Requires-Dist: requests>=2.25.0
Requires-Dist: typing-extensions>=4.0.0; python_version < '3.10'
Provides-Extra: dev
Requires-Dist: black>=22.0.0; extra == 'dev'
Requires-Dist: isort>=5.0.0; extra == 'dev'
Requires-Dist: mypy>=1.0.0; extra == 'dev'
Requires-Dist: pytest-cov>=4.0.0; extra == 'dev'
Requires-Dist: pytest>=7.0.0; extra == 'dev'
